labthings_sangaboard/__init__.py
labthings_sangaboard/server.py
labthings_sangaboard-0.0.1.dist-info/LICENSE
labthings_sangaboard-0.0.1.dist-info/METADATA
labthings_sangaboard-0.0.1.dist-info/WHEEL
labthings_sangaboard-0.0.1.dist-info/top_level.txt
labthings_sangaboard-0.0.1.dist-info/RECORD
